kaiju_tools/__init__.py
kaiju_tools/annotations.py
kaiju_tools/app.py
kaiju_tools/cache.py
kaiju_tools/context_vars.py
kaiju_tools/docker.py
kaiju_tools/encoding.py
kaiju_tools/exceptions.py
kaiju_tools/functions.py
kaiju_tools/http.py
kaiju_tools/interfaces.py
kaiju_tools/jsonschema.py
kaiju_tools/locks.py
kaiju_tools/logging.py
kaiju_tools/mapping.py
kaiju_tools/registry.py
kaiju_tools/rpc.py
kaiju_tools/rpc_client_gen.py
kaiju_tools/services.py
kaiju_tools/sessions.py
kaiju_tools/streams.py
kaiju_tools/templates.py
kaiju_tools/types.py
kaiju_tools/tests/__init__.py
kaiju_tools/tests/fixtures.py
kaiju_tools/tests/test_annotation_parser.py
kaiju_tools/tests/test_cache.py
kaiju_tools/tests/test_class_registry.py
kaiju_tools/tests/test_configurator.py
kaiju_tools/tests/test_data_store.py
kaiju_tools/tests/test_http.py
kaiju_tools/tests/test_jsonschema.py
kaiju_tools/tests/test_locks.py
kaiju_tools/tests/test_mapping.py
kaiju_tools/tests/test_rpc.py
kaiju_tools/tests/test_scheduler.py
kaiju_tools/tests/test_serializers.py
kaiju_tools/tests/test_services.py
kaiju_tools/tests/test_streams.py
kaiju_tools/tests/test_templates.py
kaiju_tools/tests/resources/__init__.py
kaiju_tools-2.4.19.dist-info/licenses/LICENSE
kaiju_tools-2.4.19.dist-info/METADATA
kaiju_tools-2.4.19.dist-info/WHEEL
kaiju_tools-2.4.19.dist-info/top_level.txt
kaiju_tools-2.4.19.dist-info/RECORD
