Metadata-Version: 2.4
Name: kaiju-tools
Version: 2.4.19
Summary: Base classes and services for a backend application
Author-email: Taraskin Anton <antonnidhoggr@me.com>
Maintainer-email: Taraskin Anton <antonnidhoggr@me.com>
Project-URL: Homepage, https://gitlab.com/kaiju-python/kaiju-tools
Project-URL: Documentation, http://kaiju-tools.readthedocs.io
Keywords: kaiju
Classifier: Development Status :: 4 - Beta
Classifier: Programming Language :: Python :: 3
Classifier: Programming Language :: Python :: 3 :: Only
Classifier: Programming Language :: Python :: Implementation :: CPython
Requires-Python: >=3.11
License-File: LICENSE
Requires-Dist: aiohttp<4.0
Requires-Dist: jinja2
Requires-Dist: msgspec
Requires-Dist: uvloop>=0.21; platform_system != "Windows"
Requires-Dist: aiohttp_cors
Requires-Dist: fastjsonschema
Requires-Dist: pyyaml>=6.0.1
Provides-Extra: dev
Requires-Dist: uv; extra == "dev"
Requires-Dist: pre-commit; extra == "dev"
Requires-Dist: bump-my-version; extra == "dev"
Requires-Dist: black; extra == "dev"
Requires-Dist: isort; extra == "dev"
Requires-Dist: bandit; extra == "dev"
Requires-Dist: pyupgrade; extra == "dev"
Requires-Dist: pyroma; extra == "dev"
Requires-Dist: pylint; extra == "dev"
Requires-Dist: pytest; extra == "dev"
Requires-Dist: pytest-asyncio; extra == "dev"
Requires-Dist: pytest-aiohttp; extra == "dev"
Requires-Dist: docker; extra == "dev"
Provides-Extra: docs
Requires-Dist: sphinx; extra == "docs"
Requires-Dist: python-docs-theme; extra == "docs"
Dynamic: license-file
